text2ics/__init__.py
text2ics/__main__.py
text2ics/cli.py
text2ics/converter.py
text2ics/system_prompt.py
text2ics-0.1.2.dist-info/METADATA
text2ics-0.1.2.dist-info/WHEEL
text2ics-0.1.2.dist-info/entry_points.txt
text2ics-0.1.2.dist-info/licenses/LICENSE
text2ics-0.1.2.dist-info/RECORD
