Metadata-Version: 2.4
Name: text2ics
Version: 0.1.2
Summary: A Python tool to convert unstructured text into an ICS calendar file using an LLM.
Project-URL: Homepage, https://github.com/jakob1379/text2ics
Project-URL: Repository, https://github.com/jakob1379/text2ics
Project-URL: Bug Tracker, https://github.com/jakob1379/text2ics/issues
Author-email: Jakob Stender Guldberg <jakob1379@gmail.com>
License: MIT
License-File: LICENSE
Keywords: ai,calendar,ics,llm,streamlit,text-processing
Classifier: Development Status :: 3 - Alpha
Classifier: Environment :: Console
Classifier: Environment :: Web Environment
Classifier: Intended Audience :: Developers
Classifier: License :: OSI Approved :: MIT License
Classifier: Programming Language :: Python :: 3
Classifier: Programming Language :: Python :: 3.13
Classifier: Topic :: Office/Business :: Scheduling
Classifier: Topic :: Text Processing
Requires-Python: >=3.13
Requires-Dist: icalendar>=6.3.1
Requires-Dist: litellm>=1.74.0
Requires-Dist: promptic>=5.5.1
Requires-Dist: python-dotenv>=1.1.1
Requires-Dist: streamlit>=1.46.1
Requires-Dist: tenacity>=9.1.2
Requires-Dist: typer>=0.16.0
